Metadata-Version: 2.1
Name: minicrawl
Version: 0.1
Summary: MiniCrawl is a minimalistic dungeon crawler-like 3D environment for Reinforcement and Imitation Learning research.
Home-page: https://github.com/fmalato/MiniCrawl
Download-URL: https://github.com/fmalato/MiniCrawl/archive/refs/tags/v0.1.tar.gz
Author: Federico Malato
Author-email: federico.malato@uef.fi
License: Apache-2.0
Keywords: Environment,Reinforcement,Imitation,Learning,Robotics,Gym
Classifier: Development Status :: 3 - Alpha
Classifier: Programming Language :: Python :: 3.7
Classifier: Programming Language :: Python :: 3.8
Classifier: Programming Language :: Python :: 3.9
Classifier: Programming Language :: Python :: 3.10
Requires-Python: >=3.7, <3.11
License-File: LICENSE.txt
Requires-Dist: gymnasium
Requires-Dist: miniworld
Requires-Dist: numpy
